<drawing><figures><r id="0" x="256" y="224" w="280" h="256"><a><fillColor><null/></fillColor><strokeColor><color rgba="#ff333333"/></strokeColor></a></r><r id="1" x="680" y="160" w="1" h="440"><a><fillColor><null/></fillColor></a></r><lnk id="2"><points><p colinear="true" x="520.2849123142496" y="480" c1x="0" c1y="-1" c2x="0" c2y="-1"/><p colinear="true" x="680" y="480" c1x="0" c1y="-1" c2x="0" c2y="-1"/></points><startConnector><relativeConnector id="3" relativeX="264.2849123142496" relativeY="256"><Owner><r ref="0"/></Owner></relativeConnector></startConnector><endConnector><relativeConnector id="4" relativeX="0" relativeY="320"><Owner><r ref="1"/></Owner></relativeConnector></endConnector><a><startConnectorStrategy><string>RotationalConnectorStrategy</string></startConnectorStrategy><endConnectorStrategy><string>RectilinearConnectorStrategy</string></endConnectorStrategy><endDecoration><arrowTip id="5" angle="0.35" innerRadius="11.3" outerRadius="12" isFilled="true" isStroked="false" isSolid="true"/></endDecoration><strokeColor><color rgba="#ff0000ff"/></strokeColor></a></lnk><lnk id="6"><points><p colinear="true" x="529.1147888902636" y="480" c1x="0" c1y="-20" c2x="0" c2y="-20"/><p colinear="true" x="680" y="480" c1x="0" c1y="-20" c2x="0" c2y="-20"/></points><startConnector><relativeConnector id="7" relativeX="273.11478889026364" relativeY="256"><Owner><r ref="0"/></Owner></relativeConnector></startConnector><endConnector><relativeConnector id="8" relativeX="0" relativeY="320"><Owner><r ref="1"/></Owner></relativeConnector></endConnector><a><startConnectorStrategy><string>RotationalConnectorStrategy</string></startConnectorStrategy><endConnectorStrategy><string>RectilinearConnectorStrategy</string></endConnectorStrategy><endDecoration><arrowTip ref="5"/></endDecoration><strokeColor><color rgba="#ff0000ff"/></strokeColor></a></lnk><lnk id="9"><points><p colinear="true" x="536" y="475.999329599146" c1x="0" c1y="-12" c2x="0" c2y="-12"/><p colinear="true" x="680" y="475.999329599146" c1x="0" c1y="-12" c2x="0" c2y="-12"/></points><startConnector><relativeConnector id="a" relativeX="280" relativeY="251.999329599146"><Owner><r ref="0"/></Owner></relativeConnector></startConnector><endConnector><relativeConnector id="b" relativeX="0" relativeY="315.999329599146"><Owner><r ref="1"/></Owner></relativeConnector></endConnector><a><startConnectorStrategy><string>RotationalConnectorStrategy</string></startConnectorStrategy><endConnectorStrategy><string>RectilinearConnectorStrategy</string></endConnectorStrategy><endDecoration><arrowTip ref="5"/></endDecoration><strokeColor><color rgba="#ff0000ff"/></strokeColor></a></lnk><lnk id="c"><points><p colinear="true" x="536" y="467.8377688473823" c1x="0" c1y="-9" c2x="0" c2y="-9"/><p colinear="true" x="680" y="467.8377688473823" c1x="0" c1y="-9" c2x="0" c2y="-9"/></points><startConnector><relativeConnector id="d" relativeX="280" relativeY="243.83776884738228"><Owner><r ref="0"/></Owner></relativeConnector></startConnector><endConnector><relativeConnector id="e" relativeX="0" relativeY="307.8377688473823"><Owner><r ref="1"/></Owner></relativeConnector></endConnector><a><startConnectorStrategy><string>RotationalConnectorStrategy</string></startConnectorStrategy><endConnectorStrategy><string>RectilinearConnectorStrategy</string></endConnectorStrategy><endDecoration><arrowTip ref="5"/></endDecoration><strokeColor><color rgba="#ff0000ff"/></strokeColor></a></lnk><lnk id="f"><points><p colinear="true" x="536" y="457.46983330985347" c1x="0" c1y="0" c2x="0" c2y="0"/><p colinear="true" x="680" y="457.46983330985347" c1x="0" c1y="0" c2x="0" c2y="0"/></points><startConnector><relativeConnector id="10" relativeX="280" relativeY="233.46983330985347"><Owner><r ref="0"/></Owner></relativeConnector></startConnector><endConnector><relativeConnector id="11" relativeX="0" relativeY="297.46983330985347"><Owner><r ref="1"/></Owner></relativeConnector></endConnector><a><startConnectorStrategy><string>RotationalConnectorStrategy</string></startConnectorStrategy><endConnectorStrategy><string>RectilinearConnectorStrategy</string></endConnectorStrategy><endDecoration><arrowTip ref="5"/></endDecoration><strokeColor><color rgba="#ff0000ff"/></strokeColor></a></lnk><lnk id="12"><points><p colinear="true" x="536" y="448.37030440452554" c1x="0" c1y="0" c2x="0" c2y="0"/><p colinear="true" x="680" y="448.37030440452554" c1x="0" c1y="0" c2x="0" c2y="0"/></points><startConnector><relativeConnector id="13" relativeX="280" relativeY="224.37030440452554"><Owner><r ref="0"/></Owner></relativeConnector></startConnector><endConnector><relativeConnector id="14" relativeX="0" relativeY="288.37030440452554"><Owner><r ref="1"/></Owner></relativeConnector></endConnector><a><startConnectorStrategy><string>RotationalConnectorStrategy</string></startConnectorStrategy><endConnectorStrategy><string>RectilinearConnectorStrategy</string></endConnectorStrategy><endDecoration><arrowTip ref="5"/></endDecoration><strokeColor><color rgba="#ffcc66ff"/></strokeColor></a></lnk><lnk id="15"><points><p colinear="true" x="536" y="439.3783181374631" c1x="0" c1y="0" c2x="0" c2y="0"/><p colinear="true" x="680" y="439.3783181374631" c1x="0" c1y="0" c2x="0" c2y="0"/></points><startConnector><relativeConnector id="16" relativeX="280" relativeY="215.3783181374631"><Owner><r ref="0"/></Owner></relativeConnector></startConnector><endConnector><relativeConnector id="17" relativeX="0" relativeY="279.3783181374631"><Owner><r ref="1"/></Owner></relativeConnector></endConnector><a><startConnectorStrategy><string>RotationalConnectorStrategy</string></startConnectorStrategy><endConnectorStrategy><string>RectilinearConnectorStrategy</string></endConnectorStrategy><endDecoration><arrowTip ref="5"/></endDecoration><strokeColor><color rgba="#ffcc66ff"/></strokeColor></a></lnk><lnk id="18"><points><p colinear="true" x="536" y="430.49197922192405" c1x="0" c1y="0" c2x="0" c2y="0"/><p colinear="true" x="680" y="430.49197922192405" c1x="0" c1y="0" c2x="0" c2y="0"/></points><startConnector><relativeConnector id="19" relativeX="280" relativeY="206.49197922192405"><Owner><r ref="0"/></Owner></relativeConnector></startConnector><endConnector><relativeConnector id="1a" relativeX="0" relativeY="270.49197922192405"><Owner><r ref="1"/></Owner></relativeConnector></endConnector><a><startConnectorStrategy><string>RotationalConnectorStrategy</string></startConnectorStrategy><endConnectorStrategy><string>RectilinearConnectorStrategy</string></endConnectorStrategy><endDecoration><arrowTip ref="5"/></endDecoration><strokeColor><color rgba="#ffcc66ff"/></strokeColor></a></lnk><lnk id="1b"><points><p colinear="true" x="536" y="421.7094366467221" c1x="0" c1y="0" c2x="0" c2y="0"/><p colinear="true" x="680" y="421.7094366467221" c1x="0" c1y="0" c2x="0" c2y="0"/></points><startConnector><relativeConnector id="1c" relativeX="280" relativeY="197.7094366467221"><Owner><r ref="0"/></Owner></relativeConnector></startConnector><endConnector><relativeConnector id="1d" relativeX="0" relativeY="261.7094366467221"><Owner><r ref="1"/></Owner></relativeConnector></endConnector><a><startConnectorStrategy><string>RotationalConnectorStrategy</string></startConnectorStrategy><endConnectorStrategy><string>RectilinearConnectorStrategy</string></endConnectorStrategy><endDecoration><arrowTip ref="5"/></endDecoration><strokeColor><color rgba="#ffcc66ff"/></strokeColor></a></lnk><lnk id="1e"><points><p colinear="true" x="536" y="413.02888239085087" c1x="0" c1y="0" c2x="0" c2y="0"/><p colinear="true" x="680" y="413.02888239085087" c1x="0" c1y="0" c2x="0" c2y="0"/></points><startConnector><relativeConnector id="1f" relativeX="280" relativeY="189.02888239085087"><Owner><r ref="0"/></Owner></relativeConnector></startConnector><endConnector><relativeConnector id="20" relativeX="0" relativeY="253.02888239085087"><Owner><r ref="1"/></Owner></relativeConnector></endConnector><a><startConnectorStrategy><string>RotationalConnectorStrategy</string></startConnectorStrategy><endConnectorStrategy><string>RectilinearConnectorStrategy</string></endConnectorStrategy><endDecoration><arrowTip ref="5"/></endDecoration><strokeColor><color rgba="#ffcc66ff"/></strokeColor></a></lnk><lnk id="21"><points><p colinear="true" x="536" y="404.4485501826218" c1x="0" c1y="0" c2x="0" c2y="0"/><p colinear="true" x="680" y="404.4485501826218" c1x="0" c1y="0" c2x="0" c2y="0"/></points><startConnector><relativeConnector id="22" relativeX="280" relativeY="180.44855018262177"><Owner><r ref="0"/></Owner></relativeConnector></startConnector><endConnector><relativeConnector id="23" relativeX="0" relativeY="244.44855018262177"><Owner><r ref="1"/></Owner></relativeConnector></endConnector><a><startConnectorStrategy><string>RotationalConnectorStrategy</string></startConnectorStrategy><endConnectorStrategy><string>RectilinearConnectorStrategy</string></endConnectorStrategy><endDecoration><arrowTip ref="5"/></endDecoration><strokeColor><color rgba="#ffffff00"/></strokeColor></a></lnk><lnk id="24"><points><p colinear="true" x="536" y="395.96671430150855" c1x="0" c1y="0" c2x="0" c2y="0"/><p colinear="true" x="680" y="395.96671430150855" c1x="0" c1y="0" c2x="0" c2y="0"/></points><startConnector><relativeConnector id="25" relativeX="280" relativeY="171.96671430150855"><Owner><r ref="0"/></Owner></relativeConnector></startConnector><endConnector><relativeConnector id="26" relativeX="0" relativeY="235.96671430150855"><Owner><r ref="1"/></Owner></relativeConnector></endConnector><a><startConnectorStrategy><string>RotationalConnectorStrategy</string></startConnectorStrategy><endConnectorStrategy><string>RectilinearConnectorStrategy</string></endConnectorStrategy><endDecoration><arrowTip ref="5"/></endDecoration><strokeColor><color rgba="#ffffff00"/></strokeColor></a></lnk><lnk id="27"><points><p colinear="true" x="536" y="387.5816884210513" c1x="0" c1y="0" c2x="0" c2y="0"/><p colinear="true" x="680" y="387.5816884210513" c1x="0" c1y="0" c2x="0" c2y="0"/></points><startConnector><relativeConnector id="28" relativeX="280" relativeY="163.5816884210513"><Owner><r ref="0"/></Owner></relativeConnector></startConnector><endConnector><relativeConnector id="29" relativeX="0" relativeY="227.5816884210513"><Owner><r ref="1"/></Owner></relativeConnector></endConnector><a><startConnectorStrategy><string>RotationalConnectorStrategy</string></startConnectorStrategy><endConnectorStrategy><string>RectilinearConnectorStrategy</string></endConnectorStrategy><endDecoration><arrowTip ref="5"/></endDecoration><strokeColor><color rgba="#ffffff00"/></strokeColor></a></lnk><lnk id="2a"><points><p colinear="true" x="536" y="379.2918244911561" c1x="0" c1y="0" c2x="0" c2y="0"/><p colinear="true" x="680" y="379.2918244911561" c1x="0" c1y="0" c2x="0" c2y="0"/></points><startConnector><relativeConnector id="2b" relativeX="280" relativeY="155.2918244911561"><Owner><r ref="0"/></Owner></relativeConnector></startConnector><endConnector><relativeConnector id="2c" relativeX="0" relativeY="219.2918244911561"><Owner><r ref="1"/></Owner></relativeConnector></endConnector><a><startConnectorStrategy><string>RotationalConnectorStrategy</string></startConnectorStrategy><endConnectorStrategy><string>RectilinearConnectorStrategy</string></endConnectorStrategy><endDecoration><arrowTip ref="5"/></endDecoration><strokeColor><color rgba="#ffffff00"/></strokeColor></a></lnk><lnk id="2d"><points><p colinear="true" x="536" y="371.09551165820176" c1x="0" c1y="0" c2x="0" c2y="0"/><p colinear="true" x="680" y="371.09551165820176" c1x="0" c1y="0" c2x="0" c2y="0"/></points><startConnector><relativeConnector id="2e" relativeX="280" relativeY="147.09551165820176"><Owner><r ref="0"/></Owner></relativeConnector></startConnector><endConnector><relativeConnector id="2f" relativeX="0" relativeY="211.09551165820176"><Owner><r ref="1"/></Owner></relativeConnector></endConnector><a><startConnectorStrategy><string>RotationalConnectorStrategy</string></startConnectorStrategy><endConnectorStrategy><string>RectilinearConnectorStrategy</string></endConnectorStrategy><endDecoration><arrowTip ref="5"/></endDecoration><strokeColor><color rgba="#ffffff00"/></strokeColor></a></lnk><lnk id="30"><points><p colinear="true" x="536" y="362.99117522153733" c1x="0" c1y="0" c2x="0" c2y="0"/><p colinear="true" x="680" y="362.99117522153733" c1x="0" c1y="0" c2x="0" c2y="0"/></points><startConnector><relativeConnector id="31" relativeX="280" relativeY="138.99117522153733"><Owner><r ref="0"/></Owner></relativeConnector></startConnector><endConnector><relativeConnector id="32" relativeX="0" relativeY="202.99117522153733"><Owner><r ref="1"/></Owner></relativeConnector></endConnector><a><startConnectorStrategy><string>RotationalConnectorStrategy</string></startConnectorStrategy><endConnectorStrategy><string>RectilinearConnectorStrategy</string></endConnectorStrategy><endDecoration><arrowTip ref="5"/></endDecoration><strokeColor><color rgba="#ffff8000"/></strokeColor></a></lnk><lnk id="33"><points><p colinear="true" x="536" y="354.9772756248999" c1x="-1" c1y="-9.999999747378752E-5" c2x="-1" c2y="-9.999999747378752E-5"/><p colinear="true" x="680" y="354.9772756248999" c1x="-1" c1y="-9.999999747378752E-5" c2x="-1" c2y="-9.999999747378752E-5"/></points><startConnector><relativeConnector id="34" relativeX="280" relativeY="130.9772756248999"><Owner><r ref="0"/></Owner></relativeConnector></startConnector><endConnector><relativeConnector id="35" relativeX="0" relativeY="194.9772756248999"><Owner><r ref="1"/></Owner></relativeConnector></endConnector><a><startConnectorStrategy><string>RotationalConnectorStrategy</string></startConnectorStrategy><endConnectorStrategy><string>RectilinearConnectorStrategy</string></endConnectorStrategy><endDecoration><arrowTip ref="5"/></endDecoration><strokeColor><color rgba="#ff333333"/></strokeColor></a></lnk><lnk id="36"><points><p colinear="true" x="536" y="348.03811569277707" c1x="0" c1y="-8" c2x="0" c2y="-8"/><p colinear="true" x="680" y="348.03811569277707" c1x="0" c1y="-8" c2x="0" c2y="-8"/></points><startConnector><relativeConnector id="37" relativeX="280" relativeY="124.03811569277707"><Owner><r ref="0"/></Owner></relativeConnector></startConnector><endConnector><relativeConnector id="38" relativeX="0" relativeY="188.03811569277707"><Owner><r ref="1"/></Owner></relativeConnector></endConnector><a><startConnectorStrategy><string>RotationalConnectorStrategy</string></startConnectorStrategy><endConnectorStrategy><string>RectilinearConnectorStrategy</string></endConnectorStrategy><endDecoration><arrowTip ref="5"/></endDecoration><strokeColor><color rgba="#ff333333"/></strokeColor></a></lnk><lnk id="39"><points><p colinear="true" x="536" y="339.21479863078173" c1x="0" c1y="0" c2x="0" c2y="0"/><p colinear="true" x="680" y="339.21479863078173" c1x="0" c1y="0" c2x="0" c2y="0"/></points><startConnector><relativeConnector id="3a" relativeX="280" relativeY="115.21479863078173"><Owner><r ref="0"/></Owner></relativeConnector></startConnector><endConnector><relativeConnector id="3b" relativeX="0" relativeY="179.21479863078173"><Owner><r ref="1"/></Owner></relativeConnector></endConnector><a><startConnectorStrategy><string>RotationalConnectorStrategy</string></startConnectorStrategy><endConnectorStrategy><string>RectilinearConnectorStrategy</string></endConnectorStrategy><endDecoration><arrowTip ref="5"/></endDecoration><strokeColor><color rgba="#ff333333"/></strokeColor></a></lnk><lnk id="3c"><points><p colinear="true" x="536" y="331.46330922778424" c1x="0" c1y="0" c2x="0" c2y="0"/><p colinear="true" x="680" y="331.46330922778424" c1x="0" c1y="0" c2x="0" c2y="0"/></points><startConnector><relativeConnector id="3d" relativeX="280" relativeY="107.46330922778424"><Owner><r ref="0"/></Owner></relativeConnector></startConnector><endConnector><relativeConnector id="3e" relativeX="0" relativeY="171.46330922778424"><Owner><r ref="1"/></Owner></relativeConnector></endConnector><a><startConnectorStrategy><string>RotationalConnectorStrategy</string></startConnectorStrategy><endConnectorStrategy><string>RectilinearConnectorStrategy</string></endConnectorStrategy><endDecoration><arrowTip ref="5"/></endDecoration><strokeColor><color rgba="#ff333333"/></strokeColor></a></lnk><lnk id="3f"><points><p colinear="true" x="536" y="323.79643086026033" c1x="0" c1y="0" c2x="0" c2y="0"/><p colinear="true" x="680" y="323.79643086026033" c1x="0" c1y="0" c2x="0" c2y="0"/></points><startConnector><relativeConnector id="40" relativeX="280" relativeY="99.79643086026033"><Owner><r ref="0"/></Owner></relativeConnector></startConnector><endConnector><relativeConnector id="41" relativeX="0" relativeY="163.79643086026033"><Owner><r ref="1"/></Owner></relativeConnector></endConnector><a><startConnectorStrategy><string>RotationalConnectorStrategy</string></startConnectorStrategy><endConnectorStrategy><string>RectilinearConnectorStrategy</string></endConnectorStrategy><endDecoration><arrowTip ref="5"/></endDecoration><strokeColor><color rgba="#ff333333"/></strokeColor></a></lnk><lnk id="42"><points><p colinear="true" x="536" y="316.2127856960887" c1x="0" c1y="0" c2x="0" c2y="0"/><p colinear="true" x="680" y="316.2127856960887" c1x="0" c1y="0" c2x="0" c2y="0"/></points><startConnector><relativeConnector id="43" relativeX="280" relativeY="92.2127856960887"><Owner><r ref="0"/></Owner></relativeConnector></startConnector><endConnector><relativeConnector id="44" relativeX="0" relativeY="156.2127856960887"><Owner><r ref="1"/></Owner></relativeConnector></endConnector><a><startConnectorStrategy><string>RotationalConnectorStrategy</string></startConnectorStrategy><endConnectorStrategy><string>RectilinearConnectorStrategy</string></endConnectorStrategy><endDecoration><arrowTip ref="5"/></endDecoration><strokeColor><color rgba="#ff00ff00"/></strokeColor></a></lnk><lnk id="45"><points><p colinear="true" x="536" y="308.7110256576924" c1x="0" c1y="0" c2x="0" c2y="0"/><p colinear="true" x="680" y="308.7110256576924" c1x="0" c1y="0" c2x="0" c2y="0"/></points><startConnector><relativeConnector id="46" relativeX="280" relativeY="84.7110256576924"><Owner><r ref="0"/></Owner></relativeConnector></startConnector><endConnector><relativeConnector id="47" relativeX="0" relativeY="148.7110256576924"><Owner><r ref="1"/></Owner></relativeConnector></endConnector><a><startConnectorStrategy><string>RotationalConnectorStrategy</string></startConnectorStrategy><endConnectorStrategy><string>RectilinearConnectorStrategy</string></endConnectorStrategy><endDecoration><arrowTip ref="5"/></endDecoration><strokeColor><color rgba="#ff00ff00"/></strokeColor></a></lnk><lnk id="48"><points><p colinear="true" x="536" y="301.28983162316445" c1x="0" c1y="0" c2x="0" c2y="0"/><p colinear="true" x="680" y="301.28983162316445" c1x="0" c1y="0" c2x="0" c2y="0"/></points><startConnector><relativeConnector id="49" relativeX="280" relativeY="77.28983162316445"><Owner><r ref="0"/></Owner></relativeConnector></startConnector><endConnector><relativeConnector id="4a" relativeX="0" relativeY="141.28983162316445"><Owner><r ref="1"/></Owner></relativeConnector></endConnector><a><startConnectorStrategy><string>RotationalConnectorStrategy</string></startConnectorStrategy><endConnectorStrategy><string>RectilinearConnectorStrategy</string></endConnectorStrategy><endDecoration><arrowTip ref="5"/></endDecoration><strokeColor><color rgba="#ff00ff00"/></strokeColor></a></lnk><lnk id="4b"><points><p colinear="true" x="536" y="293.9479126529744" c1x="0" c1y="0" c2x="0" c2y="0"/><p colinear="true" x="680" y="293.9479126529744" c1x="0" c1y="0" c2x="0" c2y="0"/></points><startConnector><relativeConnector id="4c" relativeX="280" relativeY="69.94791265297442"><Owner><r ref="0"/></Owner></relativeConnector></startConnector><endConnector><relativeConnector id="4d" relativeX="0" relativeY="133.94791265297442"><Owner><r ref="1"/></Owner></relativeConnector></endConnector><a><startConnectorStrategy><string>RotationalConnectorStrategy</string></startConnectorStrategy><endConnectorStrategy><string>RectilinearConnectorStrategy</string></endConnectorStrategy><endDecoration><arrowTip ref="5"/></endDecoration><strokeColor><color rgba="#ff00ff00"/></strokeColor></a></lnk><lnk id="4e"><points><p colinear="true" x="536" y="286.684005241352" c1x="0" c1y="0" c2x="0" c2y="0"/><p colinear="true" x="680" y="286.684005241352" c1x="0" c1y="0" c2x="0" c2y="0"/></points><startConnector><relativeConnector id="4f" relativeX="280" relativeY="62.684005241352"><Owner><r ref="0"/></Owner></relativeConnector></startConnector><endConnector><relativeConnector id="50" relativeX="0" relativeY="126.684005241352"><Owner><r ref="1"/></Owner></relativeConnector></endConnector><a><startConnectorStrategy><string>RotationalConnectorStrategy</string></startConnectorStrategy><endConnectorStrategy><string>RectilinearConnectorStrategy</string></endConnectorStrategy><endDecoration><arrowTip ref="5"/></endDecoration><strokeColor><color rgba="#ff00ff00"/></strokeColor></a></lnk><lnk id="51"><points><p colinear="true" x="536" y="280.39110718348644" c1x="0" c1y="0" c2x="0" c2y="0"/><p colinear="true" x="680" y="280.39110718348644" c1x="0" c1y="0" c2x="0" c2y="0"/></points><startConnector><relativeConnector id="52" relativeX="280" relativeY="56.39110718348644"><Owner><r ref="0"/></Owner></relativeConnector></startConnector><endConnector><relativeConnector id="53" relativeX="0" relativeY="120.39110718348644"><Owner><r ref="1"/></Owner></relativeConnector></endConnector><a><startConnectorStrategy><string>RotationalConnectorStrategy</string></startConnectorStrategy><endConnectorStrategy><string>RectilinearConnectorStrategy</string></endConnectorStrategy><endDecoration><arrowTip ref="5"/></endDecoration><strokeColor><color rgba="#ffff0080"/></strokeColor></a></lnk><lnk id="54"><points><p colinear="true" x="536" y="274.15617721686175" c1x="0" c1y="-8" c2x="0" c2y="-8"/><p colinear="true" x="680" y="274.15617721686175" c1x="0" c1y="-8" c2x="0" c2y="-8"/></points><startConnector><relativeConnector id="55" relativeX="280" relativeY="50.15617721686175"><Owner><r ref="0"/></Owner></relativeConnector></startConnector><endConnector><relativeConnector id="56" relativeX="0" relativeY="114.15617721686175"><Owner><r ref="1"/></Owner></relativeConnector></endConnector><a><startConnectorStrategy><string>RotationalConnectorStrategy</string></startConnectorStrategy><endConnectorStrategy><string>RectilinearConnectorStrategy</string></endConnectorStrategy><endDecoration><arrowTip ref="5"/></endDecoration><strokeColor><color rgba="#ffff0080"/></strokeColor></a></lnk><lnk id="57"><points><p colinear="true" x="536" y="266.2237348487572" c1x="0" c1y="0" c2x="0" c2y="0"/><p colinear="true" x="680" y="266.2237348487572" c1x="0" c1y="0" c2x="0" c2y="0"/></points><startConnector><relativeConnector id="58" relativeX="280" relativeY="42.2237348487572"><Owner><r ref="0"/></Owner></relativeConnector></startConnector><endConnector><relativeConnector id="59" relativeX="0" relativeY="106.2237348487572"><Owner><r ref="1"/></Owner></relativeConnector></endConnector><a><startConnectorStrategy><string>RotationalConnectorStrategy</string></startConnectorStrategy><endConnectorStrategy><string>RectilinearConnectorStrategy</string></endConnectorStrategy><endDecoration><arrowTip ref="5"/></endDecoration><strokeColor><color rgba="#ffff0080"/></strokeColor></a></lnk><lnk id="5a"><points><p colinear="true" x="536" y="259.2506728313875" c1x="0" c1y="0" c2x="0" c2y="0"/><p colinear="true" x="680" y="259.2506728313875" c1x="0" c1y="0" c2x="0" c2y="0"/></points><startConnector><relativeConnector id="5b" relativeX="280" relativeY="35.250672831387476"><Owner><r ref="0"/></Owner></relativeConnector></startConnector><endConnector><relativeConnector id="5c" relativeX="0" relativeY="99.25067283138748"><Owner><r ref="1"/></Owner></relativeConnector></endConnector><a><startConnectorStrategy><string>RotationalConnectorStrategy</string></startConnectorStrategy><endConnectorStrategy><string>RectilinearConnectorStrategy</string></endConnectorStrategy><endDecoration><arrowTip ref="5"/></endDecoration><strokeColor><color rgba="#ffff0080"/></strokeColor></a></lnk><lnk id="5d"><points><p colinear="true" x="536" y="251.49224977701124" c1x="0" c1y="0" c2x="0" c2y="0"/><p colinear="true" x="680" y="251.49224977701124" c1x="0" c1y="0" c2x="0" c2y="0"/></points><startConnector><relativeConnector id="5e" relativeX="280" relativeY="27.49224977701124"><Owner><r ref="0"/></Owner></relativeConnector></startConnector><endConnector><relativeConnector id="5f" relativeX="0" relativeY="91.49224977701124"><Owner><r ref="1"/></Owner></relativeConnector></endConnector><a><startConnectorStrategy><string>RotationalConnectorStrategy</string></startConnectorStrategy><endConnectorStrategy><string>RectilinearConnectorStrategy</string></endConnectorStrategy><endDecoration><arrowTip ref="5"/></endDecoration><strokeColor><color rgba="#ffff0080"/></strokeColor></a></lnk></figures></drawing>